{
  "btc_krw": 114900000.0,
  "btc_krw_change": 0.03,
  "btc_usd": 76842.3,
  "exchange_rate": 1516.19,
  "bok_rate": 3.5,
  "kimchi_premium": -1.38,
  "altcoins": {
    "ETH": {
      "krw": 3175000.0,
      "usd": 2094.067,
      "change": 0.25
    },
    "XRP": {
      "krw": 2034.0,
      "usd": 1.3415,
      "change": 0.15
    },
    "SOL": {
      "krw": 128400.0,
      "usd": 84.686,
      "change": 0.08
    },
    "SAND": {
      "krw": 107.0,
      "usd": 0.0706,
      "change": 0.0
    },
    "MANA": {
      "krw": 130.0,
      "usd": 0.0857,
      "change": -1.52
    },
    "DOGE": {
      "krw": 155.0,
      "usd": 0.1022,
      "change": 0.65
    },
    "WAVES": {
      "krw": 619.0,
      "usd": 0.4083,
      "change": 7.65
    }
  },
  "updated_at": "2026-05-24 11:35:50"
}